kikusan/__init__.py
kikusan/cli.py
kikusan/config.py
kikusan/download.py
kikusan/hooks.py
kikusan/lyrics.py
kikusan/navidrome.py
kikusan/notifications.py
kikusan/playlist.py
kikusan/queue.py
kikusan/reference_checker.py
kikusan/search.py
kikusan/spotify.py
kikusan/tags.py
kikusan/unavailable.py
kikusan/yt_dlp_wrapper.py
kikusan/cron/__init__.py
kikusan/cron/cli.py
kikusan/cron/config.py
kikusan/cron/scheduler.py
kikusan/cron/state.py
kikusan/cron/sync.py
kikusan/plugins/__init__.py
kikusan/plugins/base.py
kikusan/plugins/billboard.py
kikusan/plugins/cli.py
kikusan/plugins/listenbrainz.py
kikusan/plugins/reddit.py
kikusan/plugins/registry.py
kikusan/plugins/rss.py
kikusan/plugins/state.py
kikusan/plugins/sync.py
kikusan/web/__init__.py
kikusan/web/app.py
kikusan/web/static/favicon.ico
kikusan/web/static/style.css
kikusan/web/templates/index.html
kikusan-0.13.0.dist-info/METADATA
kikusan-0.13.0.dist-info/WHEEL
kikusan-0.13.0.dist-info/entry_points.txt
kikusan-0.13.0.dist-info/licenses/LICENSE
kikusan-0.13.0.dist-info/RECORD
