Metadata-Version: 2.4
Name: kikusan
Version: 0.13.0
Summary: Search and download music from YouTube Music with lyrics
License-File: LICENSE
Requires-Python: >=3.12
Requires-Dist: apscheduler>=3.10.4
Requires-Dist: beautifulsoup4>=4.12.0
Requires-Dist: billboard-py>=7.1.0
Requires-Dist: click>=8.0.0
Requires-Dist: croniter>=1.3.0
Requires-Dist: fastapi[standard]>=0.115.0
Requires-Dist: httpx>=0.27.0
Requires-Dist: mutagen>=1.47.0
Requires-Dist: pyyaml>=6.0.1
Requires-Dist: spotipy>=2.24.0
Requires-Dist: yt-dlp>=2025.12.8
Requires-Dist: ytmusicapi>=1.8.0
